mlpredictor/__init__.py
mlpredictor/model.py
stevepromlpredictor-0.1.0.dist-info/METADATA
stevepromlpredictor-0.1.0.dist-info/WHEEL
stevepromlpredictor-0.1.0.dist-info/top_level.txt
stevepromlpredictor-0.1.0.dist-info/RECORD
