Metadata-Version: 2.1
Name: stevepromlpredictor
Version: 0.1.0
Summary: A simple machine learning package using scikit-learn
Author-email: Ebrahim <ebimsv0501@gmail.com>
License: MIT
Project-URL: Homepage, https://github.com/ebimsv/stevepromlpredictor
Requires-Python: >=3.6
Requires-Dist: scikit-learn>=1.0
